{
  "info": {
    "name": "NextEyeSecurity Backend - Fase 1",
    "schema": "https://schema.getpostman.com/json/collection/v2.1.0/collection.json",
    "description": "Coleccion Postman para probar todos los endpoints del backend fase prioritaria."
  },
  "variable": [
    {
      "key": "baseUrl",
      "value": "http://localhost:3000/api"
    },
    {
      "key": "admin_email",
      "value": "admin1@nexteye.com"
    },
    {
      "key": "admin_password",
      "value": "Admin123*"
    },
    {
      "key": "tecnico_email",
      "value": "tecnico1@nexteye.com"
    },
    {
      "key": "tecnico_password",
      "value": "Admin123*"
    },
    {
      "key": "admin_token",
      "value": ""
    },
    {
      "key": "tecnico_token",
      "value": ""
    },
    {
      "key": "admin_user_id",
      "value": ""
    },
    {
      "key": "technician_id",
      "value": ""
    },
    {
      "key": "created_user_id",
      "value": ""
    },
    {
      "key": "client_id",
      "value": ""
    },
    {
      "key": "supplier_id",
      "value": ""
    },
    {
      "key": "product_category_id",
      "value": ""
    },
    {
      "key": "product_id",
      "value": ""
    },
    {
      "key": "service_category_id",
      "value": ""
    },
    {
      "key": "service_id",
      "value": ""
    },
    {
      "key": "quotation_id",
      "value": ""
    },
    {
      "key": "maintenance_id",
      "value": ""
    },
    {
      "key": "source_entity",
      "value": "maintenance"
    },
    {
      "key": "temp_client_delete_id",
      "value": ""
    }
  ],
  "item": [
    {
      "name": "00 - Setup",
      "item": [
        {
          "name": "Health Check",
          "request": {
            "method": "GET",
            "header": [],
            "url": {
              "raw": "{{baseUrl}}/",
              "host": [
                "{{baseUrl}}"
              ],
              "path": []
            },
            "description": "Verifica que la API esté levantada."
          }
        },
        {
          "name": "Login Admin",
          "request": {
            "method": "POST",
            "header": [
              {
                "key": "Content-Type",
                "value": "application/json"
              }
            ],
            "url": {
              "raw": "{{baseUrl}}/auth/login",
              "host": [
                "{{baseUrl}}"
              ],
              "path": [
                "auth",
                "login"
              ]
            },
            "body": {
              "mode": "raw",
              "raw": "{\n  \"email\": \"{{admin_email}}\",\n  \"password\": \"{{admin_password}}\"\n}",
              "options": {
                "raw": {
                  "language": "json"
                }
              }
            }
          },
          "event": [
            {
              "listen": "test",
              "script": {
                "type": "text/javascript",
                "exec": [
                  "pm.test(\"Login admin OK\", function () { pm.response.to.have.status(201); });",
                  "const json = pm.response.json();",
                  "pm.collectionVariables.set(\"admin_token\", json.access_token);",
                  "pm.collectionVariables.set(\"admin_user_id\", json.user.id);"
                ]
              }
            }
          ]
        },
        {
          "name": "Login Tecnico",
          "request": {
            "method": "POST",
            "header": [
              {
                "key": "Content-Type",
                "value": "application/json"
              }
            ],
            "url": {
              "raw": "{{baseUrl}}/auth/login",
              "host": [
                "{{baseUrl}}"
              ],
              "path": [
                "auth",
                "login"
              ]
            },
            "body": {
              "mode": "raw",
              "raw": "{\n  \"email\": \"{{tecnico_email}}\",\n  \"password\": \"{{tecnico_password}}\"\n}",
              "options": {
                "raw": {
                  "language": "json"
                }
              }
            }
          },
          "event": [
            {
              "listen": "test",
              "script": {
                "type": "text/javascript",
                "exec": [
                  "pm.test(\"Login tecnico OK\", function () { pm.response.to.have.status(201); });",
                  "const json = pm.response.json();",
                  "pm.collectionVariables.set(\"tecnico_token\", json.access_token);",
                  "pm.collectionVariables.set(\"technician_id\", json.user.id);"
                ]
              }
            }
          ]
        },
        {
          "name": "Mi Perfil (Admin)",
          "request": {
            "method": "GET",
            "header": [],
            "auth": {
              "type": "bearer",
              "bearer": [
                {
                  "key": "token",
                  "value": "{{admin_token}}",
                  "type": "string"
                }
              ]
            },
            "url": {
              "raw": "{{baseUrl}}/users/me",
              "host": [
                "{{baseUrl}}"
              ],
              "path": [
                "users",
                "me"
              ]
            }
          }
        },
        {
          "name": "Mi Perfil (Tecnico)",
          "request": {
            "method": "GET",
            "header": [],
            "auth": {
              "type": "bearer",
              "bearer": [
                {
                  "key": "token",
                  "value": "{{tecnico_token}}",
                  "type": "string"
                }
              ]
            },
            "url": {
              "raw": "{{baseUrl}}/users/me",
              "host": [
                "{{baseUrl}}"
              ],
              "path": [
                "users",
                "me"
              ]
            }
          }
        }
      ]
    },
    {
      "name": "01 - Users",
      "item": [
        {
          "name": "Crear Usuario",
          "request": {
            "method": "POST",
            "header": [
              {
                "key": "Content-Type",
                "value": "application/json"
              }
            ],
            "auth": {
              "type": "bearer",
              "bearer": [
                {
                  "key": "token",
                  "value": "{{admin_token}}",
                  "type": "string"
                }
              ]
            },
            "url": {
              "raw": "{{baseUrl}}/users",
              "host": [
                "{{baseUrl}}"
              ],
              "path": [
                "users"
              ]
            },
            "body": {
              "mode": "raw",
              "raw": "{\n  \"email\": \"nuevo.tecnico@nexteye.com\",\n  \"fullName\": \"Tecnico Pruebas Postman\",\n  \"password\": \"Admin123*\",\n  \"role\": \"TECNICO\",\n  \"phone\": \"0991111111\",\n  \"active\": true\n}",
              "options": {
                "raw": {
                  "language": "json"
                }
              }
            }
          },
          "event": [
            {
              "listen": "test",
              "script": {
                "type": "text/javascript",
                "exec": [
                  "pm.test(\"Usuario creado\", function () { pm.expect([200,201]).to.include(pm.response.code); });",
                  "const json = pm.response.json();",
                  "pm.collectionVariables.set(\"created_user_id\", json.id);"
                ]
              }
            }
          ]
        },
        {
          "name": "Listar Usuarios",
          "request": {
            "method": "GET",
            "header": [],
            "auth": {
              "type": "bearer",
              "bearer": [
                {
                  "key": "token",
                  "value": "{{admin_token}}",
                  "type": "string"
                }
              ]
            },
            "url": {
              "raw": "{{baseUrl}}/users",
              "host": [
                "{{baseUrl}}"
              ],
              "path": [
                "users"
              ]
            }
          }
        },
        {
          "name": "Obtener Usuario por ID",
          "request": {
            "method": "GET",
            "header": [],
            "auth": {
              "type": "bearer",
              "bearer": [
                {
                  "key": "token",
                  "value": "{{admin_token}}",
                  "type": "string"
                }
              ]
            },
            "url": {
              "raw": "{{baseUrl}}/users/{{created_user_id}}",
              "host": [
                "{{baseUrl}}"
              ],
              "path": [
                "users",
                "{{created_user_id}}"
              ]
            }
          }
        },
        {
          "name": "Actualizar Usuario",
          "request": {
            "method": "PATCH",
            "header": [
              {
                "key": "Content-Type",
                "value": "application/json"
              }
            ],
            "auth": {
              "type": "bearer",
              "bearer": [
                {
                  "key": "token",
                  "value": "{{admin_token}}",
                  "type": "string"
                }
              ]
            },
            "url": {
              "raw": "{{baseUrl}}/users/{{created_user_id}}",
              "host": [
                "{{baseUrl}}"
              ],
              "path": [
                "users",
                "{{created_user_id}}"
              ]
            },
            "body": {
              "mode": "raw",
              "raw": "{\n  \"fullName\": \"Tecnico Pruebas Postman Actualizado\",\n  \"phone\": \"0992222222\"\n}",
              "options": {
                "raw": {
                  "language": "json"
                }
              }
            }
          }
        },
        {
          "name": "Actualizar Mi Perfil",
          "request": {
            "method": "PATCH",
            "header": [
              {
                "key": "Content-Type",
                "value": "application/json"
              }
            ],
            "auth": {
              "type": "bearer",
              "bearer": [
                {
                  "key": "token",
                  "value": "{{tecnico_token}}",
                  "type": "string"
                }
              ]
            },
            "url": {
              "raw": "{{baseUrl}}/users/me/profile",
              "host": [
                "{{baseUrl}}"
              ],
              "path": [
                "users",
                "me",
                "profile"
              ]
            },
            "body": {
              "mode": "raw",
              "raw": "{\n  \"fullName\": \"Tecnico 1 Editado desde Postman\",\n  \"phone\": \"0981999999\"\n}",
              "options": {
                "raw": {
                  "language": "json"
                }
              }
            }
          }
        },
        {
          "name": "Eliminar Usuario",
          "request": {
            "method": "DELETE",
            "header": [],
            "auth": {
              "type": "bearer",
              "bearer": [
                {
                  "key": "token",
                  "value": "{{admin_token}}",
                  "type": "string"
                }
              ]
            },
            "url": {
              "raw": "{{baseUrl}}/users/{{created_user_id}}",
              "host": [
                "{{baseUrl}}"
              ],
              "path": [
                "users",
                "{{created_user_id}}"
              ]
            }
          }
        }
      ]
    },
    {
      "name": "02 - Clients",
      "item": [
        {
          "name": "Crear Cliente",
          "request": {
            "method": "POST",
            "header": [
              {
                "key": "Content-Type",
                "value": "application/json"
              }
            ],
            "auth": {
              "type": "bearer",
              "bearer": [
                {
                  "key": "token",
                  "value": "{{admin_token}}",
                  "type": "string"
                }
              ]
            },
            "url": {
              "raw": "{{baseUrl}}/clients",
              "host": [
                "{{baseUrl}}"
              ],
              "path": [
                "clients"
              ]
            },
            "body": {
              "mode": "raw",
              "raw": "{\n  \"nameOrBusinessName\": \"Cliente Demo Postman\",\n  \"documentNumber\": \"0999999999001\",\n  \"phone\": \"042000111\",\n  \"email\": \"cliente.postman@demo.com\",\n  \"address\": \"Av. Principal 123\",\n  \"city\": \"Guayaquil\",\n  \"commercialReference\": \"Cliente de pruebas\",\n  \"observations\": \"Creado desde Postman\",\n  \"active\": true\n}",
              "options": {
                "raw": {
                  "language": "json"
                }
              }
            }
          },
          "event": [
            {
              "listen": "test",
              "script": {
                "type": "text/javascript",
                "exec": [
                  "const json = pm.response.json();",
                  "pm.collectionVariables.set(\"client_id\", json.id);"
                ]
              }
            }
          ]
        },
        {
          "name": "Listar Clientes",
          "request": {
            "method": "GET",
            "header": [],
            "auth": {
              "type": "bearer",
              "bearer": [
                {
                  "key": "token",
                  "value": "{{admin_token}}",
                  "type": "string"
                }
              ]
            },
            "url": {
              "raw": "{{baseUrl}}/clients",
              "host": [
                "{{baseUrl}}"
              ],
              "path": [
                "clients"
              ]
            }
          }
        },
        {
          "name": "Obtener Cliente por ID",
          "request": {
            "method": "GET",
            "header": [],
            "auth": {
              "type": "bearer",
              "bearer": [
                {
                  "key": "token",
                  "value": "{{admin_token}}",
                  "type": "string"
                }
              ]
            },
            "url": {
              "raw": "{{baseUrl}}/clients/{{client_id}}",
              "host": [
                "{{baseUrl}}"
              ],
              "path": [
                "clients",
                "{{client_id}}"
              ]
            }
          }
        },
        {
          "name": "Actualizar Cliente",
          "request": {
            "method": "PATCH",
            "header": [
              {
                "key": "Content-Type",
                "value": "application/json"
              }
            ],
            "auth": {
              "type": "bearer",
              "bearer": [
                {
                  "key": "token",
                  "value": "{{admin_token}}",
                  "type": "string"
                }
              ]
            },
            "url": {
              "raw": "{{baseUrl}}/clients/{{client_id}}",
              "host": [
                "{{baseUrl}}"
              ],
              "path": [
                "clients",
                "{{client_id}}"
              ]
            },
            "body": {
              "mode": "raw",
              "raw": "{\n  \"city\": \"Samborondon\",\n  \"observations\": \"Cliente actualizado por Postman\"\n}",
              "options": {
                "raw": {
                  "language": "json"
                }
              }
            }
          }
        }
      ]
    },
    {
      "name": "03 - Suppliers",
      "item": [
        {
          "name": "Crear Proveedor",
          "request": {
            "method": "POST",
            "header": [
              {
                "key": "Content-Type",
                "value": "application/json"
              }
            ],
            "auth": {
              "type": "bearer",
              "bearer": [
                {
                  "key": "token",
                  "value": "{{admin_token}}",
                  "type": "string"
                }
              ]
            },
            "url": {
              "raw": "{{baseUrl}}/suppliers",
              "host": [
                "{{baseUrl}}"
              ],
              "path": [
                "suppliers"
              ]
            },
            "body": {
              "mode": "raw",
              "raw": "{\n  \"businessName\": \"Proveedor Demo Postman\",\n  \"ruc\": \"1799999999001\",\n  \"contact\": \"Ana Compras\",\n  \"phone\": \"022000111\",\n  \"email\": \"proveedor.postman@demo.com\",\n  \"address\": \"Av. Industrial\",\n  \"city\": \"Quito\",\n  \"active\": true\n}",
              "options": {
                "raw": {
                  "language": "json"
                }
              }
            }
          },
          "event": [
            {
              "listen": "test",
              "script": {
                "type": "text/javascript",
                "exec": [
                  "const json = pm.response.json();",
                  "pm.collectionVariables.set(\"supplier_id\", json.id);"
                ]
              }
            }
          ]
        },
        {
          "name": "Listar Proveedores",
          "request": {
            "method": "GET",
            "header": [],
            "auth": {
              "type": "bearer",
              "bearer": [
                {
                  "key": "token",
                  "value": "{{admin_token}}",
                  "type": "string"
                }
              ]
            },
            "url": {
              "raw": "{{baseUrl}}/suppliers",
              "host": [
                "{{baseUrl}}"
              ],
              "path": [
                "suppliers"
              ]
            }
          }
        },
        {
          "name": "Obtener Proveedor por ID",
          "request": {
            "method": "GET",
            "header": [],
            "auth": {
              "type": "bearer",
              "bearer": [
                {
                  "key": "token",
                  "value": "{{admin_token}}",
                  "type": "string"
                }
              ]
            },
            "url": {
              "raw": "{{baseUrl}}/suppliers/{{supplier_id}}",
              "host": [
                "{{baseUrl}}"
              ],
              "path": [
                "suppliers",
                "{{supplier_id}}"
              ]
            }
          }
        },
        {
          "name": "Actualizar Proveedor",
          "request": {
            "method": "PATCH",
            "header": [
              {
                "key": "Content-Type",
                "value": "application/json"
              }
            ],
            "auth": {
              "type": "bearer",
              "bearer": [
                {
                  "key": "token",
                  "value": "{{admin_token}}",
                  "type": "string"
                }
              ]
            },
            "url": {
              "raw": "{{baseUrl}}/suppliers/{{supplier_id}}",
              "host": [
                "{{baseUrl}}"
              ],
              "path": [
                "suppliers",
                "{{supplier_id}}"
              ]
            },
            "body": {
              "mode": "raw",
              "raw": "{\n  \"contact\": \"Carlos Compras\"\n}",
              "options": {
                "raw": {
                  "language": "json"
                }
              }
            }
          }
        }
      ]
    },
    {
      "name": "04 - Product Categories",
      "item": [
        {
          "name": "Crear Categoria Producto",
          "request": {
            "method": "POST",
            "header": [
              {
                "key": "Content-Type",
                "value": "application/json"
              }
            ],
            "auth": {
              "type": "bearer",
              "bearer": [
                {
                  "key": "token",
                  "value": "{{admin_token}}",
                  "type": "string"
                }
              ]
            },
            "url": {
              "raw": "{{baseUrl}}/product-categories",
              "host": [
                "{{baseUrl}}"
              ],
              "path": [
                "product-categories"
              ]
            },
            "body": {
              "mode": "raw",
              "raw": "{\n  \"name\": \"Categoria Postman Productos\",\n  \"description\": \"Categoria de pruebas\",\n  \"active\": true\n}",
              "options": {
                "raw": {
                  "language": "json"
                }
              }
            }
          },
          "event": [
            {
              "listen": "test",
              "script": {
                "type": "text/javascript",
                "exec": [
                  "const json = pm.response.json();",
                  "pm.collectionVariables.set(\"product_category_id\", json.id);"
                ]
              }
            }
          ]
        },
        {
          "name": "Listar Categorias Producto",
          "request": {
            "method": "GET",
            "header": [],
            "auth": {
              "type": "bearer",
              "bearer": [
                {
                  "key": "token",
                  "value": "{{admin_token}}",
                  "type": "string"
                }
              ]
            },
            "url": {
              "raw": "{{baseUrl}}/product-categories",
              "host": [
                "{{baseUrl}}"
              ],
              "path": [
                "product-categories"
              ]
            }
          }
        },
        {
          "name": "Obtener Categoria Producto por ID",
          "request": {
            "method": "GET",
            "header": [],
            "auth": {
              "type": "bearer",
              "bearer": [
                {
                  "key": "token",
                  "value": "{{admin_token}}",
                  "type": "string"
                }
              ]
            },
            "url": {
              "raw": "{{baseUrl}}/product-categories/{{product_category_id}}",
              "host": [
                "{{baseUrl}}"
              ],
              "path": [
                "product-categories",
                "{{product_category_id}}"
              ]
            }
          }
        },
        {
          "name": "Actualizar Categoria Producto",
          "request": {
            "method": "PATCH",
            "header": [
              {
                "key": "Content-Type",
                "value": "application/json"
              }
            ],
            "auth": {
              "type": "bearer",
              "bearer": [
                {
                  "key": "token",
                  "value": "{{admin_token}}",
                  "type": "string"
                }
              ]
            },
            "url": {
              "raw": "{{baseUrl}}/product-categories/{{product_category_id}}",
              "host": [
                "{{baseUrl}}"
              ],
              "path": [
                "product-categories",
                "{{product_category_id}}"
              ]
            },
            "body": {
              "mode": "raw",
              "raw": "{\n  \"description\": \"Descripcion actualizada\"\n}",
              "options": {
                "raw": {
                  "language": "json"
                }
              }
            }
          }
        }
      ]
    },
    {
      "name": "05 - Products",
      "item": [
        {
          "name": "Crear Producto",
          "request": {
            "method": "POST",
            "header": [
              {
                "key": "Content-Type",
                "value": "application/json"
              }
            ],
            "auth": {
              "type": "bearer",
              "bearer": [
                {
                  "key": "token",
                  "value": "{{admin_token}}",
                  "type": "string"
                }
              ]
            },
            "url": {
              "raw": "{{baseUrl}}/products",
              "host": [
                "{{baseUrl}}"
              ],
              "path": [
                "products"
              ]
            },
            "body": {
              "mode": "raw",
              "raw": "{\n  \"categoryId\": \"{{product_category_id}}\",\n  \"mainSupplierId\": \"{{supplier_id}}\",\n  \"internalCode\": \"POSTMAN-PRD-001\",\n  \"name\": \"Producto Demo Postman\",\n  \"brand\": \"Marca Demo\",\n  \"model\": \"Modelo Demo\",\n  \"description\": \"Producto creado para pruebas de API\",\n  \"baseCost\": \"150.00\",\n  \"stock\": \"10\",\n  \"unit\": \"UNIDAD\",\n  \"imageUrl\": \"https://example.com/producto.jpg\",\n  \"active\": true\n}",
              "options": {
                "raw": {
                  "language": "json"
                }
              }
            }
          },
          "event": [
            {
              "listen": "test",
              "script": {
                "type": "text/javascript",
                "exec": [
                  "const json = pm.response.json();",
                  "pm.collectionVariables.set(\"product_id\", json.id);"
                ]
              }
            }
          ]
        },
        {
          "name": "Listar Productos",
          "request": {
            "method": "GET",
            "header": [],
            "auth": {
              "type": "bearer",
              "bearer": [
                {
                  "key": "token",
                  "value": "{{admin_token}}",
                  "type": "string"
                }
              ]
            },
            "url": {
              "raw": "{{baseUrl}}/products",
              "host": [
                "{{baseUrl}}"
              ],
              "path": [
                "products"
              ]
            }
          }
        },
        {
          "name": "Obtener Producto por ID",
          "request": {
            "method": "GET",
            "header": [],
            "auth": {
              "type": "bearer",
              "bearer": [
                {
                  "key": "token",
                  "value": "{{admin_token}}",
                  "type": "string"
                }
              ]
            },
            "url": {
              "raw": "{{baseUrl}}/products/{{product_id}}",
              "host": [
                "{{baseUrl}}"
              ],
              "path": [
                "products",
                "{{product_id}}"
              ]
            }
          }
        },
        {
          "name": "Actualizar Producto",
          "request": {
            "method": "PATCH",
            "header": [
              {
                "key": "Content-Type",
                "value": "application/json"
              }
            ],
            "auth": {
              "type": "bearer",
              "bearer": [
                {
                  "key": "token",
                  "value": "{{admin_token}}",
                  "type": "string"
                }
              ]
            },
            "url": {
              "raw": "{{baseUrl}}/products/{{product_id}}",
              "host": [
                "{{baseUrl}}"
              ],
              "path": [
                "products",
                "{{product_id}}"
              ]
            },
            "body": {
              "mode": "raw",
              "raw": "{\n  \"description\": \"Producto actualizado desde Postman\",\n  \"stock\": \"20\"\n}",
              "options": {
                "raw": {
                  "language": "json"
                }
              }
            }
          }
        }
      ]
    },
    {
      "name": "06 - Service Categories",
      "item": [
        {
          "name": "Crear Categoria Servicio",
          "request": {
            "method": "POST",
            "header": [
              {
                "key": "Content-Type",
                "value": "application/json"
              }
            ],
            "auth": {
              "type": "bearer",
              "bearer": [
                {
                  "key": "token",
                  "value": "{{admin_token}}",
                  "type": "string"
                }
              ]
            },
            "url": {
              "raw": "{{baseUrl}}/service-categories",
              "host": [
                "{{baseUrl}}"
              ],
              "path": [
                "service-categories"
              ]
            },
            "body": {
              "mode": "raw",
              "raw": "{\n  \"name\": \"Categoria Postman Servicios\",\n  \"description\": \"Categoria de pruebas\",\n  \"active\": true\n}",
              "options": {
                "raw": {
                  "language": "json"
                }
              }
            }
          },
          "event": [
            {
              "listen": "test",
              "script": {
                "type": "text/javascript",
                "exec": [
                  "const json = pm.response.json();",
                  "pm.collectionVariables.set(\"service_category_id\", json.id);"
                ]
              }
            }
          ]
        },
        {
          "name": "Listar Categorias Servicio",
          "request": {
            "method": "GET",
            "header": [],
            "auth": {
              "type": "bearer",
              "bearer": [
                {
                  "key": "token",
                  "value": "{{admin_token}}",
                  "type": "string"
                }
              ]
            },
            "url": {
              "raw": "{{baseUrl}}/service-categories",
              "host": [
                "{{baseUrl}}"
              ],
              "path": [
                "service-categories"
              ]
            }
          }
        },
        {
          "name": "Obtener Categoria Servicio por ID",
          "request": {
            "method": "GET",
            "header": [],
            "auth": {
              "type": "bearer",
              "bearer": [
                {
                  "key": "token",
                  "value": "{{admin_token}}",
                  "type": "string"
                }
              ]
            },
            "url": {
              "raw": "{{baseUrl}}/service-categories/{{service_category_id}}",
              "host": [
                "{{baseUrl}}"
              ],
              "path": [
                "service-categories",
                "{{service_category_id}}"
              ]
            }
          }
        },
        {
          "name": "Actualizar Categoria Servicio",
          "request": {
            "method": "PATCH",
            "header": [
              {
                "key": "Content-Type",
                "value": "application/json"
              }
            ],
            "auth": {
              "type": "bearer",
              "bearer": [
                {
                  "key": "token",
                  "value": "{{admin_token}}",
                  "type": "string"
                }
              ]
            },
            "url": {
              "raw": "{{baseUrl}}/service-categories/{{service_category_id}}",
              "host": [
                "{{baseUrl}}"
              ],
              "path": [
                "service-categories",
                "{{service_category_id}}"
              ]
            },
            "body": {
              "mode": "raw",
              "raw": "{\n  \"description\": \"Descripcion actualizada desde Postman\"\n}",
              "options": {
                "raw": {
                  "language": "json"
                }
              }
            }
          }
        }
      ]
    },
    {
      "name": "07 - Services",
      "item": [
        {
          "name": "Crear Servicio",
          "request": {
            "method": "POST",
            "header": [
              {
                "key": "Content-Type",
                "value": "application/json"
              }
            ],
            "auth": {
              "type": "bearer",
              "bearer": [
                {
                  "key": "token",
                  "value": "{{admin_token}}",
                  "type": "string"
                }
              ]
            },
            "url": {
              "raw": "{{baseUrl}}/services",
              "host": [
                "{{baseUrl}}"
              ],
              "path": [
                "services"
              ]
            },
            "body": {
              "mode": "raw",
              "raw": "{\n  \"categoryId\": \"{{service_category_id}}\",\n  \"name\": \"Servicio Demo Postman\",\n  \"description\": \"Servicio creado para pruebas\",\n  \"baseCost\": \"75.00\",\n  \"active\": true\n}",
              "options": {
                "raw": {
                  "language": "json"
                }
              }
            }
          },
          "event": [
            {
              "listen": "test",
              "script": {
                "type": "text/javascript",
                "exec": [
                  "const json = pm.response.json();",
                  "pm.collectionVariables.set(\"service_id\", json.id);"
                ]
              }
            }
          ]
        },
        {
          "name": "Listar Servicios",
          "request": {
            "method": "GET",
            "header": [],
            "auth": {
              "type": "bearer",
              "bearer": [
                {
                  "key": "token",
                  "value": "{{admin_token}}",
                  "type": "string"
                }
              ]
            },
            "url": {
              "raw": "{{baseUrl}}/services",
              "host": [
                "{{baseUrl}}"
              ],
              "path": [
                "services"
              ]
            }
          }
        },
        {
          "name": "Obtener Servicio por ID",
          "request": {
            "method": "GET",
            "header": [],
            "auth": {
              "type": "bearer",
              "bearer": [
                {
                  "key": "token",
                  "value": "{{admin_token}}",
                  "type": "string"
                }
              ]
            },
            "url": {
              "raw": "{{baseUrl}}/services/{{service_id}}",
              "host": [
                "{{baseUrl}}"
              ],
              "path": [
                "services",
                "{{service_id}}"
              ]
            }
          }
        },
        {
          "name": "Actualizar Servicio",
          "request": {
            "method": "PATCH",
            "header": [
              {
                "key": "Content-Type",
                "value": "application/json"
              }
            ],
            "auth": {
              "type": "bearer",
              "bearer": [
                {
                  "key": "token",
                  "value": "{{admin_token}}",
                  "type": "string"
                }
              ]
            },
            "url": {
              "raw": "{{baseUrl}}/services/{{service_id}}",
              "host": [
                "{{baseUrl}}"
              ],
              "path": [
                "services",
                "{{service_id}}"
              ]
            },
            "body": {
              "mode": "raw",
              "raw": "{\n  \"description\": \"Servicio actualizado desde Postman\",\n  \"baseCost\": \"95.00\"\n}",
              "options": {
                "raw": {
                  "language": "json"
                }
              }
            }
          }
        }
      ]
    },
    {
      "name": "08 - Quotation Settings",
      "item": [
        {
          "name": "Obtener Parametros de Cotizacion",
          "request": {
            "method": "GET",
            "header": [],
            "auth": {
              "type": "bearer",
              "bearer": [
                {
                  "key": "token",
                  "value": "{{admin_token}}",
                  "type": "string"
                }
              ]
            },
            "url": {
              "raw": "{{baseUrl}}/quotation-settings",
              "host": [
                "{{baseUrl}}"
              ],
              "path": [
                "quotation-settings"
              ]
            }
          }
        },
        {
          "name": "Actualizar Parametros de Cotizacion",
          "request": {
            "method": "PATCH",
            "header": [
              {
                "key": "Content-Type",
                "value": "application/json"
              }
            ],
            "auth": {
              "type": "bearer",
              "bearer": [
                {
                  "key": "token",
                  "value": "{{admin_token}}",
                  "type": "string"
                }
              ]
            },
            "url": {
              "raw": "{{baseUrl}}/quotation-settings",
              "host": [
                "{{baseUrl}}"
              ],
              "path": [
                "quotation-settings"
              ]
            },
            "body": {
              "mode": "raw",
              "raw": "{\n  \"currentVat\": \"15\",\n  \"allowedVatRates\": [\n    \"0\",\n    \"1\",\n    \"12\",\n    \"15\"\n  ],\n  \"allowedMargins\": [\n    \"10\",\n    \"12\",\n    \"20\",\n    \"25\",\n    \"30\"\n  ],\n  \"defaultMargin\": \"20\",\n  \"defaultCurrency\": \"USD\",\n  \"defaultValidityDays\": 20\n}",
              "options": {
                "raw": {
                  "language": "json"
                }
              }
            }
          }
        }
      ]
    },
    {
      "name": "09 - Quotations",
      "item": [
        {
          "name": "Crear Cotizacion",
          "request": {
            "method": "POST",
            "header": [
              {
                "key": "Content-Type",
                "value": "application/json"
              }
            ],
            "auth": {
              "type": "bearer",
              "bearer": [
                {
                  "key": "token",
                  "value": "{{admin_token}}",
                  "type": "string"
                }
              ]
            },
            "url": {
              "raw": "{{baseUrl}}/quotations",
              "host": [
                "{{baseUrl}}"
              ],
              "path": [
                "quotations"
              ]
            },
            "body": {
              "mode": "raw",
              "raw": "{\n  \"clientId\": \"{{client_id}}\",\n  \"status\": \"BORRADOR\",\n  \"observations\": \"Cotizacion de prueba Postman\",\n  \"discount\": \"10.00\",\n  \"currency\": \"USD\",\n  \"items\": [\n    {\n      \"itemType\": \"PRODUCTO\",\n      \"productId\": \"{{product_id}}\",\n      \"quantity\": \"2\",\n      \"vatPercent\": \"15\",\n      \"marginPercent\": \"20\"\n    },\n    {\n      \"itemType\": \"SERVICIO\",\n      \"serviceId\": \"{{service_id}}\",\n      \"quantity\": \"1\",\n      \"vatPercent\": \"0\",\n      \"marginPercent\": \"20\"\n    }\n  ]\n}",
              "options": {
                "raw": {
                  "language": "json"
                }
              }
            }
          },
          "event": [
            {
              "listen": "test",
              "script": {
                "type": "text/javascript",
                "exec": [
                  "const json = pm.response.json();",
                  "pm.collectionVariables.set(\"quotation_id\", json.id);"
                ]
              }
            }
          ]
        },
        {
          "name": "Listar Cotizaciones",
          "request": {
            "method": "GET",
            "header": [],
            "auth": {
              "type": "bearer",
              "bearer": [
                {
                  "key": "token",
                  "value": "{{admin_token}}",
                  "type": "string"
                }
              ]
            },
            "url": {
              "raw": "{{baseUrl}}/quotations",
              "host": [
                "{{baseUrl}}"
              ],
              "path": [
                "quotations"
              ]
            }
          }
        },
        {
          "name": "Obtener Cotizacion por ID",
          "request": {
            "method": "GET",
            "header": [],
            "auth": {
              "type": "bearer",
              "bearer": [
                {
                  "key": "token",
                  "value": "{{admin_token}}",
                  "type": "string"
                }
              ]
            },
            "url": {
              "raw": "{{baseUrl}}/quotations/{{quotation_id}}",
              "host": [
                "{{baseUrl}}"
              ],
              "path": [
                "quotations",
                "{{quotation_id}}"
              ]
            }
          }
        },
        {
          "name": "Actualizar Estado Cotizacion",
          "request": {
            "method": "PATCH",
            "header": [
              {
                "key": "Content-Type",
                "value": "application/json"
              }
            ],
            "auth": {
              "type": "bearer",
              "bearer": [
                {
                  "key": "token",
                  "value": "{{admin_token}}",
                  "type": "string"
                }
              ]
            },
            "url": {
              "raw": "{{baseUrl}}/quotations/{{quotation_id}}/status",
              "host": [
                "{{baseUrl}}"
              ],
              "path": [
                "quotations",
                "{{quotation_id}}",
                "status"
              ]
            },
            "body": {
              "mode": "raw",
              "raw": "{\n  \"status\": \"ENVIADA\"\n}",
              "options": {
                "raw": {
                  "language": "json"
                }
              }
            }
          }
        },
        {
          "name": "Descargar PDF Cotizacion",
          "request": {
            "method": "GET",
            "header": [],
            "auth": {
              "type": "bearer",
              "bearer": [
                {
                  "key": "token",
                  "value": "{{admin_token}}",
                  "type": "string"
                }
              ]
            },
            "url": {
              "raw": "{{baseUrl}}/quotations/{{quotation_id}}/pdf",
              "host": [
                "{{baseUrl}}"
              ],
              "path": [
                "quotations",
                "{{quotation_id}}",
                "pdf"
              ]
            },
            "description": "Debe devolver binary PDF con Content-Type application/pdf."
          }
        }
      ]
    },
    {
      "name": "10 - Maintenance",
      "item": [
        {
          "name": "Crear Mantenimiento",
          "request": {
            "method": "POST",
            "header": [
              {
                "key": "Content-Type",
                "value": "application/json"
              }
            ],
            "auth": {
              "type": "bearer",
              "bearer": [
                {
                  "key": "token",
                  "value": "{{admin_token}}",
                  "type": "string"
                }
              ]
            },
            "url": {
              "raw": "{{baseUrl}}/maintenance",
              "host": [
                "{{baseUrl}}"
              ],
              "path": [
                "maintenance"
              ]
            },
            "body": {
              "mode": "raw",
              "raw": "{\n  \"clientId\": \"{{client_id}}\",\n  \"type\": \"PREVENTIVO\",\n  \"status\": \"PENDIENTE\",\n  \"scheduledDate\": \"2026-03-20\",\n  \"technicianId\": \"{{technician_id}}\",\n  \"intervenedSystem\": \"Sistema CCTV\",\n  \"diagnosis\": \"Diagnostico inicial desde Postman\",\n  \"appliedSolution\": \"Ajuste de configuracion\",\n  \"observations\": \"Registro de prueba\"\n}",
              "options": {
                "raw": {
                  "language": "json"
                }
              }
            }
          },
          "event": [
            {
              "listen": "test",
              "script": {
                "type": "text/javascript",
                "exec": [
                  "const json = pm.response.json();",
                  "pm.collectionVariables.set(\"maintenance_id\", json.id);"
                ]
              }
            }
          ]
        },
        {
          "name": "Listar Mantenimientos",
          "request": {
            "method": "GET",
            "header": [],
            "auth": {
              "type": "bearer",
              "bearer": [
                {
                  "key": "token",
                  "value": "{{admin_token}}",
                  "type": "string"
                }
              ]
            },
            "url": {
              "raw": "{{baseUrl}}/maintenance",
              "host": [
                "{{baseUrl}}"
              ],
              "path": [
                "maintenance"
              ]
            }
          }
        },
        {
          "name": "Obtener Mantenimiento por ID",
          "request": {
            "method": "GET",
            "header": [],
            "auth": {
              "type": "bearer",
              "bearer": [
                {
                  "key": "token",
                  "value": "{{admin_token}}",
                  "type": "string"
                }
              ]
            },
            "url": {
              "raw": "{{baseUrl}}/maintenance/{{maintenance_id}}",
              "host": [
                "{{baseUrl}}"
              ],
              "path": [
                "maintenance",
                "{{maintenance_id}}"
              ]
            }
          }
        },
        {
          "name": "Actualizar Mantenimiento",
          "request": {
            "method": "PATCH",
            "header": [
              {
                "key": "Content-Type",
                "value": "application/json"
              }
            ],
            "auth": {
              "type": "bearer",
              "bearer": [
                {
                  "key": "token",
                  "value": "{{admin_token}}",
                  "type": "string"
                }
              ]
            },
            "url": {
              "raw": "{{baseUrl}}/maintenance/{{maintenance_id}}",
              "host": [
                "{{baseUrl}}"
              ],
              "path": [
                "maintenance",
                "{{maintenance_id}}"
              ]
            },
            "body": {
              "mode": "raw",
              "raw": "{\n  \"status\": \"EN_PROCESO\",\n  \"executionDate\": \"2026-03-21\"\n}",
              "options": {
                "raw": {
                  "language": "json"
                }
              }
            }
          }
        }
      ]
    },
    {
      "name": "11 - Maintenance Comments",
      "item": [
        {
          "name": "Crear Comentario de Mantenimiento",
          "request": {
            "method": "POST",
            "header": [
              {
                "key": "Content-Type",
                "value": "application/json"
              }
            ],
            "auth": {
              "type": "bearer",
              "bearer": [
                {
                  "key": "token",
                  "value": "{{admin_token}}",
                  "type": "string"
                }
              ]
            },
            "url": {
              "raw": "{{baseUrl}}/maintenance-comments",
              "host": [
                "{{baseUrl}}"
              ],
              "path": [
                "maintenance-comments"
              ]
            },
            "body": {
              "mode": "raw",
              "raw": "{\n  \"maintenanceId\": \"{{maintenance_id}}\",\n  \"comment\": \"Comentario tecnico de prueba desde Postman\"\n}",
              "options": {
                "raw": {
                  "language": "json"
                }
              }
            }
          }
        },
        {
          "name": "Listar Comentarios por Mantenimiento",
          "request": {
            "method": "GET",
            "header": [],
            "auth": {
              "type": "bearer",
              "bearer": [
                {
                  "key": "token",
                  "value": "{{admin_token}}",
                  "type": "string"
                }
              ]
            },
            "url": {
              "raw": "{{baseUrl}}/maintenance-comments/maintenance/{{maintenance_id}}",
              "host": [
                "{{baseUrl}}"
              ],
              "path": [
                "maintenance-comments",
                "maintenance",
                "{{maintenance_id}}"
              ]
            }
          }
        }
      ]
    },
    {
      "name": "12 - Attachments",
      "item": [
        {
          "name": "Crear Adjunto (Metadatos)",
          "request": {
            "method": "POST",
            "header": [
              {
                "key": "Content-Type",
                "value": "application/json"
              }
            ],
            "auth": {
              "type": "bearer",
              "bearer": [
                {
                  "key": "token",
                  "value": "{{admin_token}}",
                  "type": "string"
                }
              ]
            },
            "url": {
              "raw": "{{baseUrl}}/attachments",
              "host": [
                "{{baseUrl}}"
              ],
              "path": [
                "attachments"
              ]
            },
            "body": {
              "mode": "raw",
              "raw": "{\n  \"sourceEntity\": \"{{source_entity}}\",\n  \"sourceEntityId\": \"{{maintenance_id}}\",\n  \"originalName\": \"foto_evidencia.jpg\",\n  \"storedName\": \"foto_evidencia_001.jpg\",\n  \"mimeType\": \"image/jpeg\",\n  \"storagePath\": \"/uploads/maintenance/foto_evidencia_001.jpg\",\n  \"size\": \"2048\"\n}",
              "options": {
                "raw": {
                  "language": "json"
                }
              }
            }
          }
        },
        {
          "name": "Listar Adjuntos por Entidad",
          "request": {
            "method": "GET",
            "header": [],
            "auth": {
              "type": "bearer",
              "bearer": [
                {
                  "key": "token",
                  "value": "{{admin_token}}",
                  "type": "string"
                }
              ]
            },
            "url": {
              "raw": "{{baseUrl}}/attachments/{{source_entity}}/{{maintenance_id}}",
              "host": [
                "{{baseUrl}}"
              ],
              "path": [
                "attachments",
                "{{source_entity}}",
                "{{maintenance_id}}"
              ]
            }
          }
        }
      ]
    },
    {
      "name": "13 - Audit Logs",
      "item": [
        {
          "name": "Listar Auditoria",
          "request": {
            "method": "GET",
            "header": [],
            "auth": {
              "type": "bearer",
              "bearer": [
                {
                  "key": "token",
                  "value": "{{admin_token}}",
                  "type": "string"
                }
              ]
            },
            "url": {
              "raw": "{{baseUrl}}/audit-logs",
              "host": [
                "{{baseUrl}}"
              ],
              "path": [
                "audit-logs"
              ],
              "query": [
                {
                  "key": "limit",
                  "value": "100"
                }
              ]
            }
          }
        }
      ]
    },
    {
      "name": "99 - Cleanup (DELETE Endpoints)",
      "item": [
        {
          "name": "Eliminar Mantenimiento",
          "request": {
            "method": "DELETE",
            "header": [],
            "auth": {
              "type": "bearer",
              "bearer": [
                {
                  "key": "token",
                  "value": "{{admin_token}}",
                  "type": "string"
                }
              ]
            },
            "url": {
              "raw": "{{baseUrl}}/maintenance/{{maintenance_id}}",
              "host": [
                "{{baseUrl}}"
              ],
              "path": [
                "maintenance",
                "{{maintenance_id}}"
              ]
            }
          }
        },
        {
          "name": "Eliminar Servicio",
          "request": {
            "method": "DELETE",
            "header": [],
            "auth": {
              "type": "bearer",
              "bearer": [
                {
                  "key": "token",
                  "value": "{{admin_token}}",
                  "type": "string"
                }
              ]
            },
            "url": {
              "raw": "{{baseUrl}}/services/{{service_id}}",
              "host": [
                "{{baseUrl}}"
              ],
              "path": [
                "services",
                "{{service_id}}"
              ]
            }
          }
        },
        {
          "name": "Eliminar Categoria Servicio",
          "request": {
            "method": "DELETE",
            "header": [],
            "auth": {
              "type": "bearer",
              "bearer": [
                {
                  "key": "token",
                  "value": "{{admin_token}}",
                  "type": "string"
                }
              ]
            },
            "url": {
              "raw": "{{baseUrl}}/service-categories/{{service_category_id}}",
              "host": [
                "{{baseUrl}}"
              ],
              "path": [
                "service-categories",
                "{{service_category_id}}"
              ]
            }
          }
        },
        {
          "name": "Eliminar Producto",
          "request": {
            "method": "DELETE",
            "header": [],
            "auth": {
              "type": "bearer",
              "bearer": [
                {
                  "key": "token",
                  "value": "{{admin_token}}",
                  "type": "string"
                }
              ]
            },
            "url": {
              "raw": "{{baseUrl}}/products/{{product_id}}",
              "host": [
                "{{baseUrl}}"
              ],
              "path": [
                "products",
                "{{product_id}}"
              ]
            }
          }
        },
        {
          "name": "Eliminar Categoria Producto",
          "request": {
            "method": "DELETE",
            "header": [],
            "auth": {
              "type": "bearer",
              "bearer": [
                {
                  "key": "token",
                  "value": "{{admin_token}}",
                  "type": "string"
                }
              ]
            },
            "url": {
              "raw": "{{baseUrl}}/product-categories/{{product_category_id}}",
              "host": [
                "{{baseUrl}}"
              ],
              "path": [
                "product-categories",
                "{{product_category_id}}"
              ]
            }
          }
        },
        {
          "name": "Eliminar Proveedor",
          "request": {
            "method": "DELETE",
            "header": [],
            "auth": {
              "type": "bearer",
              "bearer": [
                {
                  "key": "token",
                  "value": "{{admin_token}}",
                  "type": "string"
                }
              ]
            },
            "url": {
              "raw": "{{baseUrl}}/suppliers/{{supplier_id}}",
              "host": [
                "{{baseUrl}}"
              ],
              "path": [
                "suppliers",
                "{{supplier_id}}"
              ]
            }
          }
        },
        {
          "name": "Crear Cliente Temporal para DELETE",
          "request": {
            "method": "POST",
            "header": [
              {
                "key": "Content-Type",
                "value": "application/json"
              }
            ],
            "auth": {
              "type": "bearer",
              "bearer": [
                {
                  "key": "token",
                  "value": "{{admin_token}}",
                  "type": "string"
                }
              ]
            },
            "url": {
              "raw": "{{baseUrl}}/clients",
              "host": [
                "{{baseUrl}}"
              ],
              "path": [
                "clients"
              ]
            },
            "body": {
              "mode": "raw",
              "raw": "{\n  \"nameOrBusinessName\": \"Cliente Temporal DELETE\",\n  \"documentNumber\": \"0999999999777\",\n  \"phone\": \"042000777\",\n  \"email\": \"tmp.delete@nexteye.com\",\n  \"address\": \"Direccion temporal\",\n  \"city\": \"Guayaquil\",\n  \"active\": true\n}",
              "options": {
                "raw": {
                  "language": "json"
                }
              }
            }
          },
          "event": [
            {
              "listen": "test",
              "script": {
                "type": "text/javascript",
                "exec": [
                  "const json = pm.response.json();",
                  "pm.collectionVariables.set(\"temp_client_delete_id\", json.id);"
                ]
              }
            }
          ]
        },
        {
          "name": "Eliminar Cliente (Temporal)",
          "request": {
            "method": "DELETE",
            "header": [],
            "auth": {
              "type": "bearer",
              "bearer": [
                {
                  "key": "token",
                  "value": "{{admin_token}}",
                  "type": "string"
                }
              ]
            },
            "url": {
              "raw": "{{baseUrl}}/clients/{{temp_client_delete_id}}",
              "host": [
                "{{baseUrl}}"
              ],
              "path": [
                "clients",
                "{{temp_client_delete_id}}"
              ]
            }
          }
        }
      ]
    }
  ]
}